rolfdog/__init__.py
rolfdog/jtools1.py
rolfdog/jtools2.py
rolfdog-0.0.5.dist-info/LICENSE
rolfdog-0.0.5.dist-info/METADATA
rolfdog-0.0.5.dist-info/WHEEL
rolfdog-0.0.5.dist-info/top_level.txt
rolfdog-0.0.5.dist-info/RECORD
